seq_detect_mealy.v
module seq_detect_mealy(
    input wire clk,
    input wire rst,
    input wire din,
    output wire y
);
localparam S0 = 2'b00; 
localparam S1 = 2'b01; 
localparam S2 = 2'b10; 
localparam S3 = 2'b11; 
reg [1:0] current_state, next_state;

always @(posedge clk) begin
    if (rst) begin
        current_state <= S0;
    end else begin
        current_state <= next_state;
    end
end

always @(*) begin
    next_state = current_state; 
    case (current_state)
        S0: if (din == 1'b1) next_state = S1;
        S1: if (din == 1'b0) next_state = S0;
            else next_state = S2;
        S2: if (din == 1'b0) next_state = S3;
            else next_state = S2;
        S3: if (din == 1'b0) next_state = S0;
            else next_state = S1;
        default: next_state = S0;
    endcase
end

assign y = (current_state == S3) && (din == 1'b1);

endmodule

fsm-assignments/problem1_seqdet/tb_seq_detect_mealy.v
module tb_seq_detect_mealy;

reg clk, rst, din;
wire y;

seq_detect_mealy dut(.clk(clk), .rst(rst), .din(din), .y(y));


initial begin
    clk = 0;
    forever #5 clk = ~clk; 
end

initial begin
    $dumpfile("tb_seq_detect_mealy");
    $dumpvars(0, tb_seq_detect_mealy);
end

initial begin
    rst = 1;
    din = 0;
    #10 rst = 0;

    #10 din = 1; 
    #10 din = 1; 
    #10 din = 0; 
    #10 din = 1; 
    #10 din = 1; 
    #10 din = 0; 
    #10 din = 1;
    #10 din = 1;
   
    #10 din = 1;
   
    #10 din = 0;
    
    #10 din = 1; 

    #50 $finish; 
end

endmodule

fsm-assignments/problem1_seqdet/tb_seq_detect_mealy.vcd
$date
	Tue Aug 19 21:45:01 2025
$end
$version
	Icarus Verilog
$end
$timescale
	1s
$end
$scope module tb_seq_detect_mealy $end
$var wire 1 ! y $end
$var reg 1 " clk $end
$var reg 1 # din $end
$var reg 1 $ rst $end
$scope module dut $end
$var wire 1 " clk $end
$var wire 1 # din $end
$var wire 1 $ rst $end
$var wire 1 ! y $end
$var parameter 2 % S0 $end
$var parameter 2 & S1 $end
$var parameter 2 ' S2 $end
$var parameter 2 ( S3 $end
$var reg 2 ) current_state [1:0] $end
$var reg 2 * next_state [1:0] $end
$upscope $end
$upscope $end
$enddefinitions $end
$comment Show the parameter values. $end
$dumpall
b11 (
b10 '
b1 &
b0 %
$end
#0
$dumpvars
b0 *
bx )
1$
0#
0"
0!
$end
#5
b0 )
1"
#10
0"
0$
#15
1"
#20
b1 *
0"
1#
#25
b10 *
b1 )
1"
#30
0"
#35
b10 )
1"
#40
b11 *
0"
0#
#45
b0 *
b11 )
1"
#50
1!
b1 *
0"
1#
#55
b10 *
0!
b1 )
1"
#60
0"
#65
b10 )
1"
#70
b11 *
0"
0#
#75
b0 *
b11 )
1"
#80
1!
b1 *
0"
1#
#85
b10 *
0!
b1 )
1"
#90
0"
#95
b10 )
1"
#100
0"
#105
1"
#110
b11 *
0"
0#
#115
b0 *
b11 )
1"
#120
1!
b1 *
0"
1#
#125
b10 *
0!
b1 )
1"
#130
0"
#135
b10 )
1"
