fsm-assignments/probelm4_link/slave_fsm.v
module slave_fsm(
    input wire clk,
    input wire rst,
    input wire req,
    input wire [7:0] data_in,
    output wire ack,
    output wire [7:0] last_byte
);

localparam IDLE = 2'b00;
localparam GOT_REQ = 2'b01;
localparam ACK_HOLD1 = 2'b10;
localparam ACK_HOLD2 = 2'b11;

reg [1:0] current_state, next_state;
reg ack_reg;
reg [7:0] last_byte_reg;

always @(posedge clk) begin
    if (rst) begin
        current_state <= IDLE;
        ack_reg <= 0;
    end else begin
        current_state <= next_state;
    end
end

always @(*) begin
    next_state = current_state;
    case (current_state)
        IDLE: begin
            if (req) begin
                last_byte_reg = data_in; 
                ack_reg = 1;
                next_state = GOT_REQ;
            end
        end
        GOT_REQ: begin
            ack_reg = 1;
            next_state = ACK_HOLD1;
        end
        ACK_HOLD1: begin
            ack_reg = 1;
            next_state = ACK_HOLD2;
        end
        ACK_HOLD2: begin
            ack_reg = 1;
            if (!req) begin
                ack_reg = 0;
                next_state = IDLE;
            end
        end
        default: begin
            next_state = IDLE;
            ack_reg = 0;
        end
    endcase
end

assign ack = ack_reg;
assign last_byte = last_byte_reg;

endmodule

fsm-assignments/probelm4_link/master_fsm.v
module master_fsm(
    input wire clk,
    input wire rst,
    input wire ack,
    output wire req,
    output wire [7:0] data,
    output wire done
);

localparam IDLE = 3'b000;
localparam REQ = 3'b001;
localparam WAIT_ACK = 3'b010;
localparam WAIT_ACK_DROP = 3'b011;
localparam DONE_STATE = 3'b100;

reg [2:0] current_state, next_state;
reg [1:0] byte_index;
reg [7:0] data_reg;
reg req_reg;
reg done_reg;

always @(posedge clk) begin
    if (rst) begin
        current_state <= IDLE;
        byte_index <= 0;
    end else begin
        current_state <= next_state;
        if ((current_state == WAIT_ACK_DROP) && (byte_index < 3)) begin
            byte_index <= byte_index + 1;
        end
    end
end

always @(*) begin
    next_state = current_state;
    case (current_state)
        IDLE: begin
            req_reg = 0;
            done_reg = 0;
 
            next_state = REQ;
        end
        REQ: begin
            req_reg = 1;
            next_state = WAIT_ACK;
        end
        WAIT_ACK: begin
            req_reg = 1;
            if (ack) next_state = WAIT_ACK_DROP;
        end
        WAIT_ACK_DROP: begin
            req_reg = 0;
            if (!ack) begin
                if (byte_index == 3) next_state = DONE_STATE;
                else next_state = REQ;
            end
        end
        DONE_STATE: begin
            done_reg = 1;
            next_state = IDLE;
        end
        default: begin
            next_state = IDLE;
            req_reg = 0;
            done_reg = 0;
        end
    endcase
end

assign req = req_reg;
assign data = data_reg;
assign done = done_reg;

endmodule

fsm-assignments/probelm4_link/link_top.v
module link_top(
    input wire clk,
    input wire rst,
    output wire done
);

wire req, ack;
wire [7:0] data;
wire [7:0] last_byte;

master_fsm u_master (
    .clk(clk),
    .rst(rst),
    .ack(ack),
    .req(req),
    .data(data),
    .done(done)
);

slave_fsm u_slave (
    .clk(clk),
    .rst(rst),
    .req(req),
    .data_in(data),
    .ack(ack),
    .last_byte(last_byte)
);

endmodule

fsm-assignments/probelm4_link/tb_link_top.v
module tb_link_top;

reg clk, rst;
wire done;

link_top dut(.clk(clk), .rst(rst), .done(done));

// Clock generation
initial begin
    clk = 0;
    forever #5 clk = ~clk;
end

initial begin
    $dumpfile("tb_top_link.vcd");
    $dumpvars(0, tb_link_top);
end

initial begin
    rst = 1;
    #10 rst = 0;

    @(posedge done);

    #10 $finish;
end

endmodule

fsm-assignments/probelm4_link/tb_top_link.vcd
$date
	Tue Aug 19 22:27:57 2025
$end
$version
	Icarus Verilog
$end
$timescale
	1s
$end
$scope module tb_link_top $end
$var wire 1 ! done $end
$var reg 1 " clk $end
$var reg 1 # rst $end
$scope module dut $end
$var wire 1 " clk $end
$var wire 1 # rst $end
$var wire 1 $ req $end
$var wire 8 % last_byte [7:0] $end
$var wire 1 ! done $end
$var wire 8 & data [7:0] $end
$var wire 1 ' ack $end
$scope module u_master $end
$var wire 1 " clk $end
$var wire 8 ( data [7:0] $end
$var wire 1 ! done $end
$var wire 1 $ req $end
$var wire 1 # rst $end
$var wire 1 ' ack $end
$var parameter 3 ) DONE_STATE $end
$var parameter 3 * IDLE $end
$var parameter 3 + REQ $end
$var parameter 3 , WAIT_ACK $end
$var parameter 3 - WAIT_ACK_DROP $end
$var reg 2 . byte_index [1:0] $end
$var reg 3 / current_state [2:0] $end
$var reg 8 0 data_reg [7:0] $end
$var reg 1 1 done_reg $end
$var reg 3 2 next_state [2:0] $end
$var reg 1 3 req_reg $end
$upscope $end
$scope module u_slave $end
$var wire 1 ' ack $end
$var wire 1 " clk $end
$var wire 8 4 data_in [7:0] $end
$var wire 8 5 last_byte [7:0] $end
$var wire 1 $ req $end
$var wire 1 # rst $end
$var parameter 2 6 ACK_HOLD1 $end
$var parameter 2 7 ACK_HOLD2 $end
$var parameter 2 8 GOT_REQ $end
$var parameter 2 9 IDLE $end
$var reg 1 : ack_reg $end
$var reg 2 ; current_state [1:0] $end
$var reg 8 < last_byte_reg [7:0] $end
$var reg 2 = next_state [1:0] $end
$upscope $end
$upscope $end
$upscope $end
$enddefinitions $end
$comment Show the parameter values. $end
$dumpall
b0 9
b1 8
b11 7
b10 6
b11 -
b10 ,
b1 +
b0 *
b100 )
$end
#0
$dumpvars
bx =
bx <
bx ;
x:
bx 5
bx 4
x3
bx 2
x1
bx 0
bx /
bx .
bx (
x'
bx &
bx %
x$
1#
0"
x!
$end
#5
0!
01
0$
03
b1 2
b0 =
b0 .
b0 /
0'
0:
b0 ;
1"
#10
0"
0#
#15
b1 =
1'
1:
b10 2
1$
13
b1 /
1"
#20
0"
#25
b11 2
b10 =
b10 /
b1 ;
1"
#30
0"
#35
b11 =
0$
03
b10 ;
b11 /
1"
#40
0"
#45
b1 2
b0 =
0'
0:
b1 .
b11 ;
1"
#50
0"
#55
b1 =
1'
1:
b10 2
1$
13
b0 ;
b10 .
b1 /
1"
#60
0"
#65
b11 2
b10 =
b10 /
b1 ;
1"
#70
0"
#75
b11 =
0$
03
b10 ;
b11 /
1"
#80
0"
#85
b100 2
b0 =
0'
0:
b11 .
b11 ;
1"
#90
0"
#95
b0 2
1!
11
b0 ;
b100 /
1"
#100
0"
#105
b1 2
0!
01
b0 /
1"
