fsm-assignments/problem2_traffic/traffic_light.v
module traffic_light(
    input wire clk,
    input wire rst,
    input wire tick,
    output wire ns_g,
    output wire ns_y,
    output wire ns_r,
    output wire ew_g,
    output wire ew_y,
    output wire ew_r
);

localparam NS_G_STATE = 2'b00;
localparam NS_Y_STATE = 2'b01;
localparam EW_G_STATE = 2'b10;
localparam EW_Y_STATE = 2'b11;

reg [1:0] current_state, next_state;
reg [3:0] counter; // 4 bits for a max count of 15

always @(posedge clk) begin
    if (rst) begin
        current_state <= NS_G_STATE;
        counter <= 0;
    end else begin
        current_state <= next_state;
        if (tick) begin
            counter <= counter + 1;
        end
    end
end

always @(*) begin
    next_state = current_state;
    case (current_state)
        NS_G_STATE: if (counter == 5-1) next_state = NS_Y_STATE;
        NS_Y_STATE: if (counter == 2-1) next_state = EW_G_STATE;
        EW_G_STATE: if (counter == 5-1) next_state = EW_Y_STATE;
        EW_Y_STATE: if (counter == 2-1) next_state = NS_G_STATE;
    endcase
end

assign ns_g = (current_state == NS_G_STATE);
assign ns_y = (current_state == NS_Y_STATE);
assign ns_r = (current_state == EW_G_STATE) || (current_state == EW_Y_STATE);

assign ew_g = (current_state == EW_G_STATE);
assign ew_y = (current_state == EW_Y_STATE);
assign ew_r = (current_state == NS_G_STATE) || (current_state == NS_Y_STATE);

endmodule

fsm-assignments/problem2_traffic/tick_prescaler.v

module tick_prescaler #(
    parameter integer CLK_FREQ_HZ = 50_000_000,
    parameter integer TICK_HZ = 1
) (
    input wire clk,
    input wire rst,
    output wire tick
);

localparam integer TERMINAL_COUNT = CLK_FREQ_HZ / TICK_HZ;

reg [31:0] counter;
reg tick_reg;

always @(posedge clk) begin
    if (rst) begin
        counter <= 0;
        tick_reg <= 0;
    end else begin
        if (counter == TERMINAL_COUNT - 1) begin
            counter <= 0;
            tick_reg <= 1;
        end else begin
            counter <= counter + 1;
            tick_reg <= 0;
        end
    end
end

assign tick = tick_reg;

endmodule

fsm-assignments/problem2_traffic/tb_traffic_light.v
module tb_traffic_light;

reg clk, rst;
wire tick;

wire ns_g, ns_y, ns_r;
wire ew_g, ew_y, ew_r;

tick_prescaler #(
    .CLK_FREQ_HZ(100),
    .TICK_HZ(5)
) u_prescaler (
    .clk(clk),
    .rst(rst),
    .tick(tick)
);

traffic_light dut(
    .clk(clk), .rst(rst), .tick(tick),
    .ns_g(ns_g), .ns_y(ns_y), .ns_r(ns_r),
    .ew_g(ew_g), .ew_y(ew_y), .ew_r(ew_r)
);

initial begin
    clk = 0;
    forever #5 clk = ~clk; 
end

initial begin
    $dumpfile("tb_traffic_light");
    $dumpvars(0, tb_traffic_light);
end

initial begin
    rst = 1;
    #10 rst = 0;

    #2000 $finish;
end

endmodule

fsm-assignments/problem2_traffic/tb_traffic_light.vcd
$date
	Tue Aug 19 22:03:08 2025
$end
$version
	Icarus Verilog
$end
$timescale
	1s
$end
$scope module tb_traffic_light $end
$var wire 1 ! tick $end
$var wire 1 " ns_y $end
$var wire 1 # ns_r $end
$var wire 1 $ ns_g $end
$var wire 1 % ew_y $end
$var wire 1 & ew_r $end
$var wire 1 ' ew_g $end
$var reg 1 ( clk $end
$var reg 1 ) rst $end
$scope module dut $end
$var wire 1 ( clk $end
$var wire 1 & ew_r $end
$var wire 1 # ns_r $end
$var wire 1 ) rst $end
$var wire 1 ! tick $end
$var wire 1 " ns_y $end
$var wire 1 $ ns_g $end
$var wire 1 % ew_y $end
$var wire 1 ' ew_g $end
$var parameter 2 * EW_G_STATE $end
$var parameter 2 + EW_Y_STATE $end
$var parameter 2 , NS_G_STATE $end
$var parameter 2 - NS_Y_STATE $end
$var reg 4 . counter [3:0] $end
$var reg 2 / current_state [1:0] $end
$var reg 2 0 next_state [1:0] $end
$upscope $end
$scope module u_prescaler $end
$var wire 1 ( clk $end
$var wire 1 ) rst $end
$var wire 1 ! tick $end
$var parameter 32 1 CLK_FREQ_HZ $end
$var parameter 32 2 TERMINAL_COUNT $end
$var parameter 32 3 TICK_HZ $end
$var reg 32 4 counter [31:0] $end
$var reg 1 5 tick_reg $end
$upscope $end
$upscope $end
$enddefinitions $end
$comment Show the parameter values. $end
$dumpall
b101 3
b10100 2
b1100100 1
b1 -
b0 ,
b11 +
b10 *
$end
#0
$dumpvars
x5
bx 4
bx 0
bx /
bx .
1)
0(
x'
x&
x%
x$
x#
x"
x!
$end
#5
b0 0
0#
1&
0!
05
b0 4
b0 .
1$
0"
0'
0%
b0 /
1(
#10
0(
0)
#15
b1 4
1(
#20
0(
#25
b10 4
1(
#30
0(
#35
b11 4
1(
#40
0(
#45
b100 4
1(
#50
0(
#55
b101 4
1(
#60
0(
#65
b110 4
1(
#70
0(
#75
b111 4
1(
#80
0(
#85
b1000 4
1(
#90
0(
#95
b1001 4
1(
#100
0(
#105
b1010 4
1(
#110
0(
#115
b1011 4
1(
#120
0(
#125
b1100 4
1(
#130
0(
#135
b1101 4
1(
#140
0(
#145
b1110 4
1(
#150
0(
#155
b1111 4
1(
#160
0(
#165
b10000 4
1(
#170
0(
#175
b10001 4
1(
#180
0(
#185
b10010 4
1(
#190
0(
#195
b10011 4
1(
#200
0(
#205
1!
15
b0 4
1(
#210
0(
#215
b1 .
0!
05
b1 4
1(
#220
0(
#225
b10 4
1(
#230
0(
#235
b11 4
1(
#240
0(
#245
b100 4
1(
#250
0(
#255
b101 4
1(
#260
0(
#265
b110 4
1(
#270
0(
#275
b111 4
1(
#280
0(
#285
b1000 4
1(
#290
0(
#295
b1001 4
1(
#300
0(
#305
b1010 4
1(
#310
0(
#315
b1011 4
1(
#320
0(
#325
b1100 4
1(
#330
0(
#335
b1101 4
1(
#340
0(
#345
b1110 4
1(
#350
0(
#355
b1111 4
1(
#360
0(
#365
b10000 4
1(
#370
0(
#375
b10001 4
1(
#380
0(
#385
b10010 4
1(
#390
0(
#395
b10011 4
1(
#400
0(
#405
1!
15
b0 4
1(
#410
0(
#415
b10 .
0!
05
b1 4
1(
#420
0(
#425
b10 4
1(
#430
0(
#435
b11 4
1(
#440
0(
#445
b100 4
1(
#450
0(
#455
b101 4
1(
#460
0(
#465
b110 4
1(
#470
0(
#475
b111 4
1(
#480
0(
#485
b1000 4
1(
#490
0(
#495
b1001 4
1(
#500
0(
#505
b1010 4
1(
#510
0(
#515
b1011 4
1(
#520
0(
#525
b1100 4
1(
#530
0(
#535
b1101 4
1(
#540
0(
#545
b1110 4
1(
#550
0(
#555
b1111 4
1(
#560
0(
#565
b10000 4
1(
#570
0(
#575
b10001 4
1(
#580
0(
#585
b10010 4
1(
#590
0(
#595
b10011 4
1(
#600
0(
#605
1!
15
b0 4
1(
#610
0(
#615
b11 .
0!
05
b1 4
1(
#620
0(
#625
b10 4
1(
#630
0(
#635
b11 4
1(
#640
0(
#645
b100 4
1(
#650
0(
#655
b101 4
1(
#660
0(
#665
b110 4
1(
#670
0(
#675
b111 4
1(
#680
0(
#685
b1000 4
1(
#690
0(
#695
b1001 4
1(
#700
0(
#705
b1010 4
1(
#710
0(
#715
b1011 4
1(
#720
0(
#725
b1100 4
1(
#730
0(
#735
b1101 4
1(
#740
0(
#745
b1110 4
1(
#750
0(
#755
b1111 4
1(
#760
0(
#765
b10000 4
1(
#770
0(
#775
b10001 4
1(
#780
0(
#785
b10010 4
1(
#790
0(
#795
b10011 4
1(
#800
0(
#805
1!
15
b0 4
1(
#810
0(
#815
b1 0
b100 .
0!
05
b1 4
1(
#820
0(
#825
b10 4
0$
1"
b1 /
1(
#830
0(
#835
b11 4
1(
#840
0(
#845
b100 4
1(
#850
0(
#855
b101 4
1(
#860
0(
#865
b110 4
1(
#870
0(
#875
b111 4
1(
#880
0(
#885
b1000 4
1(
#890
0(
#895
b1001 4
1(
#900
0(
#905
b1010 4
1(
#910
0(
#915
b1011 4
1(
#920
0(
#925
b1100 4
1(
#930
0(
#935
b1101 4
1(
#940
0(
#945
b1110 4
1(
#950
0(
#955
b1111 4
1(
#960
0(
#965
b10000 4
1(
#970
0(
#975
b10001 4
1(
#980
0(
#985
b10010 4
1(
#990
0(
#995
b10011 4
1(
#1000
0(
#1005
1!
15
b0 4
1(
#1010
0(
#1015
b101 .
0!
05
b1 4
1(
#1020
0(
#1025
b10 4
1(
#1030
0(
#1035
b11 4
1(
#1040
0(
#1045
b100 4
1(
#1050
0(
#1055
b101 4
1(
#1060
0(
#1065
b110 4
1(
#1070
0(
#1075
b111 4
1(
#1080
0(
#1085
b1000 4
1(
#1090
0(
#1095
b1001 4
1(
#1100
0(
#1105
b1010 4
1(
#1110
0(
#1115
b1011 4
1(
#1120
0(
#1125
b1100 4
1(
#1130
0(
#1135
b1101 4
1(
#1140
0(
#1145
b1110 4
1(
#1150
0(
#1155
b1111 4
1(
#1160
0(
#1165
b10000 4
1(
#1170
0(
#1175
b10001 4
1(
#1180
0(
#1185
b10010 4
1(
#1190
0(
#1195
b10011 4
1(
#1200
0(
#1205
1!
15
b0 4
1(
#1210
0(
#1215
b110 .
0!
05
b1 4
1(
#1220
0(
#1225
b10 4
1(
#1230
0(
#1235
b11 4
1(
#1240
0(
#1245
b100 4
1(
#1250
0(
#1255
b101 4
1(
#1260
0(
#1265
b110 4
1(
#1270
0(
#1275
b111 4
1(
#1280
0(
#1285
b1000 4
1(
#1290
0(
#1295
b1001 4
1(
#1300
0(
#1305
b1010 4
1(
#1310
0(
#1315
b1011 4
1(
#1320
0(
#1325
b1100 4
1(
#1330
0(
#1335
b1101 4
1(
#1340
0(
#1345
b1110 4
1(
#1350
0(
#1355
b1111 4
1(
#1360
0(
#1365
b10000 4
1(
#1370
0(
#1375
b10001 4
1(
#1380
0(
#1385
b10010 4
1(
#1390
0(
#1395
b10011 4
1(
#1400
0(
#1405
1!
15
b0 4
1(
#1410
0(
#1415
b111 .
0!
05
b1 4
1(
#1420
0(
#1425
b10 4
1(
#1430
0(
#1435
b11 4
1(
#1440
0(
#1445
b100 4
1(
#1450
0(
#1455
b101 4
1(
#1460
0(
#1465
b110 4
1(
#1470
0(
#1475
b111 4
1(
#1480
0(
#1485
b1000 4
1(
#1490
0(
#1495
b1001 4
1(
#1500
0(
#1505
b1010 4
1(
#1510
0(
#1515
b1011 4
1(
#1520
0(
#1525
b1100 4
1(
#1530
0(
#1535
b1101 4
1(
#1540
0(
#1545
b1110 4
1(
#1550
0(
#1555
b1111 4
1(
#1560
0(
#1565
b10000 4
1(
#1570
0(
#1575
b10001 4
1(
#1580
0(
#1585
b10010 4
1(
#1590
0(
#1595
b10011 4
1(
#1600
0(
#1605
1!
15
b0 4
1(
#1610
0(
#1615
b1000 .
0!
05
b1 4
1(
#1620
0(
#1625
b10 4
1(
#1630
0(
#1635
b11 4
1(
#1640
0(
#1645
b100 4
1(
#1650
0(
#1655
b101 4
1(
#1660
0(
#1665
b110 4
1(
#1670
0(
#1675
b111 4
1(
#1680
0(
#1685
b1000 4
1(
#1690
0(
#1695
b1001 4
1(
#1700
0(
#1705
b1010 4
1(
#1710
0(
#1715
b1011 4
1(
#1720
0(
#1725
b1100 4
1(
#1730
0(
#1735
b1101 4
1(
#1740
0(
#1745
b1110 4
1(
#1750
0(
#1755
b1111 4
1(
#1760
0(
#1765
b10000 4
1(
#1770
0(
#1775
b10001 4
1(
#1780
0(
#1785
b10010 4
1(
#1790
0(
#1795
b10011 4
1(
#1800
0(
#1805
1!
15
b0 4
1(
#1810
0(
#1815
b1001 .
0!
05
b1 4
1(
#1820
0(
#1825
b10 4
1(
#1830
0(
#1835
b11 4
1(
#1840
0(
#1845
b100 4
1(
#1850
0(
#1855
b101 4
1(
#1860
0(
#1865
b110 4
1(
#1870
0(
#1875
b111 4
1(
#1880
0(
#1885
b1000 4
1(
#1890
0(
#1895
b1001 4
1(
#1900
0(
#1905
b1010 4
1(
#1910
0(
#1915
b1011 4
1(
#1920
0(
#1925
b1100 4
1(
#1930
0(
#1935
b1101 4
1(
#1940
0(
#1945
b1110 4
1(
#1950
0(
#1955
b1111 4
1(
#1960
0(
#1965
b10000 4
1(
#1970
0(
#1975
b10001 4
1(
#1980
0(
#1985
b10010 4
1(
#1990
0(
#1995
b10011 4
1(
#2000
0(
#2005
1!
15
b0 4
1(
