fsm-assignments/probelm3_vending/vending_mealy.v
module vending_mealy(
    input wire clk,
    input wire rst,
    input wire [1:0] coin, 
    output wire dispense, 
    output wire chg5      
);

localparam S0 = 3'b000;  
localparam S5 = 3'b001;  
localparam S10 = 3'b010; 
localparam S15 = 3'b011; 
localparam S20 = 3'b100; 

reg [2:0] current_state, next_state;

always @(posedge clk) begin
    if (rst) begin
        current_state <= S0;
    end else begin
        current_state <= next_state;
    end
end

always @(*) begin
    next_state = current_state;
    case (current_state)
        S0: begin
            if (coin == 2'b01) next_state = S5;
            else if (coin == 2'b10) next_state = S10;
        end
        S5: begin
            if (coin == 2'b01) next_state = S10;
            else if (coin == 2'b10) next_state = S15;
        end
        S10: begin
            if (coin == 2'b01) next_state = S15;
            else if (coin == 2'b10) next_state = S20;
        end
        S15: begin
            if (coin == 2'b01) next_state = S20;
            else if (coin == 2'b10) next_state = S0; 
        end
        S20: begin
            if (coin == 2'b01) next_state = S0; 
            else if (coin == 2'b10) next_state = S0; 
        end
        default: next_state = S0;
    endcase
end

assign dispense = ((current_state == S15) && (coin == 2'b10)) ||
                  ((current_state == S20) && (coin == 2'b01)) ||
                  ((current_state == S20) && (coin == 2'b10));

assign chg5 = ((current_state == S15) && (coin == 2'b10)) ||
              ((current_state == S20) && (coin == 2'b01));

endmodule

fsm-assignments/probelm3_vending/tb_vending_mealy.v
// File: tb_vending_mealy.v
module tb_vending_mealy;

reg clk, rst;
reg [1:0] coin;
wire dispense, chg5;

vending_mealy dut(.clk(clk), .rst(rst), .coin(coin),
                  .dispense(dispense), .chg5(chg5));

initial begin
    clk = 0;
    forever #5 clk = ~clk;
end

initial begin
    $dumpfile("tb_vending-mealy.vcd");
    $dumpvars(0, tb_vending_mealy);
end

initial begin
    // Reset
    rst = 1; coin = 2'b00;
    #10 rst = 0;

    #10 coin = 2'b01; 
    #10 coin = 2'b01; 
    #10 coin = 2'b10; 
    #10 coin = 2'b00;

    #10 coin = 2'b01; 
    #10 coin = 2'b10; 
    #10 coin = 2'b10; 
    #10 coin = 2'b00;

    #10 coin = 2'b10; 
    #10 coin = 2'b10; 
    #10 coin = 2'b00;

    #50 $finish;
end

endmodule

fsm-assignments/probelm3_vending/tb_vending-mealy.vcd
$date
	Tue Aug 19 22:15:49 2025
$end
$version
	Icarus Verilog
$end
$timescale
	1s
$end
$scope module tb_vending_mealy $end
$var wire 1 ! dispense $end
$var wire 1 " chg5 $end
$var reg 1 # clk $end
$var reg 2 $ coin [1:0] $end
$var reg 1 % rst $end
$scope module dut $end
$var wire 1 " chg5 $end
$var wire 1 # clk $end
$var wire 2 & coin [1:0] $end
$var wire 1 ! dispense $end
$var wire 1 % rst $end
$var parameter 3 ' S0 $end
$var parameter 3 ( S10 $end
$var parameter 3 ) S15 $end
$var parameter 3 * S20 $end
$var parameter 3 + S5 $end
$var reg 3 , current_state [2:0] $end
$var reg 3 - next_state [2:0] $end
$upscope $end
$upscope $end
$enddefinitions $end
$comment Show the parameter values. $end
$dumpall
b1 +
b100 *
b11 )
b10 (
b0 '
$end
#0
$dumpvars
b0 -
bx ,
b0 &
1%
b0 $
0#
0"
0!
$end
#5
b0 ,
1#
#10
0#
0%
#15
1#
#20
b1 -
0#
b1 $
b1 &
#25
b10 -
b1 ,
1#
#30
0#
#35
b11 -
b10 ,
1#
#40
b100 -
0#
b10 $
b10 &
#45
1!
b0 -
b100 ,
1#
#50
0!
b100 -
0#
b0 $
b0 &
#55
1#
#60
1!
1"
b0 -
0#
b1 $
b1 &
#65
0!
0"
b1 -
b0 ,
1#
#70
b10 -
0#
b10 $
b10 &
#75
b100 -
b10 ,
1#
#80
0#
#85
1!
b0 -
b100 ,
1#
#90
0!
b100 -
0#
b0 $
b0 &
#95
1#
#100
1!
b0 -
0#
b10 $
b10 &
#105
0!
b10 -
b0 ,
1#
#110
0#
#115
b100 -
b10 ,
1#
#120
b10 -
0#
b0 $
b0 &
